{
    "@class": "com.kony.gen.viz.model.component.KVizUserWidget",
    "DNDConfig": null,
    "_children_": [],
    "_height_": {
        "type": "string",
        "value": "100%"
    },
    "_left_": {
        "type": "string",
        "value": "0dp"
    },
    "_margin_": [
        0,
        0,
        0,
        0
    ],
    "_orientation_": 1,
    "_padding_": [
        0,
        0,
        0,
        0
    ],
    "_percent_": true,
    "_skin_": "s216801916534979a34790f5dfd3d04a",
    "_top_": {
        "type": "string",
        "value": "0dp"
    },
    "_width_": {
        "type": "string",
        "value": "100%"
    },
    "canUpdateUI": true,
    "containerweight": 0,
    "data": {},
    "id": "quitConfirm",
    "info": null,
    "iscustomlayout": false,
    "isvisible": false,
    "kuid": "f5e4d130128f426faaaa7170169ceced",
    "masterType": 1,
    "name": "kony.ui.UserWidgetInstance",
    "parent": "frmMain2",
    "pf": "frmMain2",
    "retaincontentalignment": false,
    "retainflexpositionproperties": false,
    "retainflowhorizontalalignment": false,
    "sourceUserWidget": "a82317fe9b534cc28496db784989767d",
    "wType": "UserWidgetInstance",
    "zindex": 1
}