{
    "@class": "com.kony.gen.viz.model.component.KVizUserWidget",
    "DNDConfig": null,
    "_bottom_": {
        "type": "string",
        "value": "10dp"
    },
    "_children_": [],
    "_height_": {
        "type": "string",
        "value": "30dp"
    },
    "_left_": {
        "type": "string",
        "value": "0dp"
    },
    "_margin_": [
        0,
        0,
        0,
        0
    ],
    "_orientation_": 1,
    "_padding_": [
        0,
        0,
        0,
        0
    ],
    "_percent_": true,
    "_skin_": "s24b2b59d8184d6b9f0eab0bad10f926",
    "_top_": {
        "type": "string",
        "value": "10dp"
    },
    "_width_": {
        "type": "string",
        "value": "165dp"
    },
    "canUpdateUI": true,
    "centerx": {
        "type": "string",
        "value": "50%"
    },
    "containerweight": 0,
    "data": {
        "caption": "Non, je veux continuer",
        "image": "short_right.png",
        "skinCaption": "s9ad6690a953443a8f5ee94d45e23214"
    },
    "id": "btnStay",
    "info": null,
    "iscustomlayout": false,
    "isvisible": true,
    "kuid": "e3dbc3e9c4ee43b58e4be81931019bac",
    "masterType": 1,
    "name": "kony.ui.UserWidgetInstance",
    "parent": "flxConfirm",
    "pf": "userwidgetmodel",
    "retaincontentalignment": false,
    "retainflexpositionproperties": false,
    "retainflowhorizontalalignment": false,
    "sourceUserWidget": "i045debc725d4afc8d82d7d7cf466260",
    "wType": "UserWidgetInstance",
    "zindex": 1
}